PyPlcnextRsc/__init__.py
PyPlcnextRsc/about.py
PyPlcnextRsc/Arp/__init__.py
PyPlcnextRsc/Arp/Device/__init__.py
PyPlcnextRsc/Arp/Device/Interface/__init__.py
PyPlcnextRsc/Arp/Device/Interface/Services/__init__.py
PyPlcnextRsc/Arp/Io/__init__.py
PyPlcnextRsc/Arp/Io/Axioline/__init__.py
PyPlcnextRsc/Arp/Io/Axioline/Services/__init__.py
PyPlcnextRsc/Arp/Plc/__init__.py
PyPlcnextRsc/Arp/Plc/Commons/__init__.py
PyPlcnextRsc/Arp/Plc/Domain/__init__.py
PyPlcnextRsc/Arp/Plc/Domain/Services/__init__.py
PyPlcnextRsc/Arp/Plc/Gds/__init__.py
PyPlcnextRsc/Arp/Plc/Gds/Services/__init__.py
PyPlcnextRsc/Arp/Plc/Retain/__init__.py
PyPlcnextRsc/Arp/Plc/Retain/Services/__init__.py
PyPlcnextRsc/Arp/Services/__init__.py
PyPlcnextRsc/Arp/Services/DataLogger/__init__.py
PyPlcnextRsc/Arp/Services/DataLogger/Services/__init__.py
PyPlcnextRsc/Arp/Services/NotificationLogger/__init__.py
PyPlcnextRsc/Arp/Services/NotificationLogger/Services/__init__.py
PyPlcnextRsc/Arp/Services/TraceController/__init__.py
PyPlcnextRsc/Arp/Services/TraceController/Services/__init__.py
PyPlcnextRsc/Arp/System/__init__.py
PyPlcnextRsc/Arp/System/Commons/__init__.py
PyPlcnextRsc/Arp/System/Commons/Services/__init__.py
PyPlcnextRsc/Arp/System/Commons/Services/Io/__init__.py
PyPlcnextRsc/Arp/System/Rsc/__init__.py
PyPlcnextRsc/Arp/System/Rsc/Services/__init__.py
PyPlcnextRsc/Arp/System/Security/__init__.py
PyPlcnextRsc/Arp/System/Security/Services/__init__.py
PyPlcnextRsc/common/__init__.py
PyPlcnextRsc/common/device.py
PyPlcnextRsc/common/exceptions.py
PyPlcnextRsc/common/sys_util.py
PyPlcnextRsc/common/tag_type.py
PyPlcnextRsc/common/util.py
PyPlcnextRsc/common/internalEnums/__init__.py
PyPlcnextRsc/common/internalEnums/commandType.py
PyPlcnextRsc/common/internalEnums/remotingVersion.py
PyPlcnextRsc/common/internalEnums/string_encoding.py
PyPlcnextRsc/common/objects/__init__.py
PyPlcnextRsc/common/objects/rsc_sequence.py
PyPlcnextRsc/common/objects/rsc_stream.py
PyPlcnextRsc/common/objects/rsc_struct.py
PyPlcnextRsc-0.1.14.dist-info/LICENSE
PyPlcnextRsc-0.1.14.dist-info/METADATA
PyPlcnextRsc-0.1.14.dist-info/WHEEL
PyPlcnextRsc-0.1.14.dist-info/top_level.txt
PyPlcnextRsc-0.1.14.dist-info/RECORD
