Metadata-Version: 2.1
Name: PyPlcnextRsc
Version: 0.1.14
Summary: RSC Client for PLCnext
Home-page: https://www.phoenixcontact.com/
Author: Song Yantao (PXC/IMA&STE)
Author-email: wudonglai@phoenixcontact.com.cn
License: MIT
Classifier: Topic :: Scientific/Engineering
Classifier: Development Status :: 2 - Pre-Alpha
Classifier: Operating System :: OS Independent
Classifier: Intended Audience :: Developers
Classifier: Intended Audience :: Science/Research
Classifier: Intended Audience :: Education
Classifier: Intended Audience :: Manufacturing
Classifier: Intended Audience :: Information Technology
Classifier: Natural Language :: English
Classifier: Natural Language :: Chinese (Simplified)
Classifier: License :: OSI Approved :: MIT License
Classifier: Programming Language :: Python :: 3 :: Only
Classifier: Programming Language :: Python :: 3.9
Classifier: Programming Language :: Python :: 3.8
Requires-Python: >=3.7.6
License-File: LICENSE
